Rsql-1.1-py3.7-nspkg.pth
Rsql/Rmysql.py
Rsql/Rpostgres.py
Rsql/Rsqlite.py
Rsql/test.py
Rsql-1.1.dist-info/METADATA
Rsql-1.1.dist-info/WHEEL
Rsql-1.1.dist-info/namespace_packages.txt
Rsql-1.1.dist-info/top_level.txt
Rsql-1.1.dist-info/RECORD
