Metadata-Version: 2.1
Name: Rsql
Version: 1.1
Summary: Rsql
Home-page: UNKNOWN
Author: Raf
License: MIT
Keywords: sql,sql python,clear SQL,flask SQL,MYSQL,SQLITE3,postgresql
Platform: UNKNOWN
Classifier: License :: OSI Approved :: MIT License
Classifier: Programming Language :: Python :: 3.7
Requires-Dist: PyMySQL (==0.9.3)
Requires-Dist: psycopg2 (==2.7.7)
Requires-Dist: psycopg2-binary (==2.7.7)
